Proyecto/Simulaciones/SImulaciones.v
module SImulaciones(RxData,FinalCarrera1,FinalCarrera2,LuzSwitch,Luz,Sensor,Alarma,Motor1,Motor2,clockLight);

	input [3:0]RxData;
	input FinalCarrera1;
	input FinalCarrera2;
	input LuzSwitch;
	input Sensor;
	input clockLight;
	output Luz;
	output Alarma;
	output Motor1;
	output Motor2;
		
	
	assign  Alarma = ~Sensor;
	assign Luz = !RxData[2] && !clockLight && !LuzSwitch;
	assign Motor1 = !RxData[0] || FinalCarrera1 || FinalCarrera2;
	assign Motor2 = !RxData[1] || FinalCarrera1 || FinalCarrera2;
	

	
endmodule

Proyecto/Simulaciones/SImulaciones_tb.v
module SImulaciones_tb;

	integer i;
	integer ix;
	reg FinalCarrera1,	FinalCarrera2,	LuzSwitch,	Sensor,clockLight;
    reg [3:0]RxData;
	wire Luz,Alarma, Motor1,Motor2;


    SImulaciones SImulaciones(
    .Luz(Luz),
	.Alarma(Alarma),
	.Motor1(Motor1),
	.Motor2(Motor2),
	.RxData(RxData),
	.FinalCarrera1(FinalCarrera1),
	.FinalCarrera2(FinalCarrera2),
	.LuzSwitch(LuzSwitch),
	.Sensor(Sensor),
	.clockLight(clockLight));

	initial begin
		$dumpfile("test.vcd");
		$dumpvars(0,SImulaciones_tb);
		
		
		for(ix=0;ix<31;ix=ix+1)begin
			FinalCarrera1 <= ix[0] ;
			FinalCarrera2 <= ix[1] ;
			LuzSwitch <= ix[2] ;
			clockLight <= ix[3] ;
			Sensor<= ix[4] ;
			for(i=0;i<15;i=i+1)begin
				RxData <=i;
				# 1;
			end
		end	
		
	end
endmodule

Proyecto/Simulaciones/test.vcd
$date
	Tue Sep 24 23:45:26 2024
$end
$version
	Icarus Verilog
$end
$timescale
	1s
$end
$scope module SImulaciones_tb $end
$var wire 1 ! Motor2 $end
$var wire 1 " Motor1 $end
$var wire 1 # Luz $end
$var wire 1 $ Alarma $end
$var reg 1 % FinalCarrera1 $end
$var reg 1 & FinalCarrera2 $end
$var reg 1 ' LuzSwitch $end
$var reg 4 ( RxData [3:0] $end
$var reg 1 ) Sensor $end
$var reg 1 * clockLight $end
$var integer 32 + i [31:0] $end
$var integer 32 , ix [31:0] $end
$scope module SImulaciones $end
$var wire 1 $ Alarma $end
$var wire 1 % FinalCarrera1 $end
$var wire 1 & FinalCarrera2 $end
$var wire 1 # Luz $end
$var wire 1 ' LuzSwitch $end
$var wire 1 " Motor1 $end
$var wire 1 ! Motor2 $end
$var wire 4 - RxData [3:0] $end
$var wire 1 ) Sensor $end
$var wire 1 * clockLight $end
$upscope $end
$upscope $end
$enddefinitions $end
$comment Show the parameter values. $end
$dumpall
$end
#0
$dumpvars
b0 -
b0 ,
b0 +
0*
0)
b0 (
0'
0&
0%
1$
1#
1"
1!
$end
#1
0"
b1 (
b1 -
b1 +
#2
1"
0!
b10 (
b10 -
b10 +
#3
0"
b11 (
b11 -
b11 +
#4
0#
1"
1!
b100 (
b100 -
b100 +
#5
0"
b101 (
b101 -
b101 +
#6
1"
0!
b110 (
b110 -
b110 +
#7
0"
b111 (
b111 -
b111 +
#8
1#
1"
1!
b1000 (
b1000 -
b1000 +
#9
0"
b1001 (
b1001 -
b1001 +
#10
1"
0!
b1010 (
b1010 -
b1010 +
#11
0"
b1011 (
b1011 -
b1011 +
#12
0#
1"
1!
b1100 (
b1100 -
b1100 +
#13
0"
b1101 (
b1101 -
b1101 +
#14
1"
0!
b1110 (
b1110 -
b1110 +
#15
1#
1!
b0 (
b0 -
1%
b1 ,
b0 +
#16
b1 (
b1 -
b1 +
#17
b10 (
b10 -
b10 +
#18
b11 (
b11 -
b11 +
#19
0#
b100 (
b100 -
b100 +
#20
b101 (
b101 -
b101 +
#21
b110 (
b110 -
b110 +
#22
b111 (
b111 -
b111 +
#23
1#
b1000 (
b1000 -
b1000 +
#24
b1001 (
b1001 -
b1001 +
#25
b1010 (
b1010 -
b1010 +
#26
b1011 (
b1011 -
b1011 +
#27
0#
b1100 (
b1100 -
b1100 +
#28
b1101 (
b1101 -
b1101 +
#29
b1110 (
b1110 -
b1110 +
#30
1#
b0 (
b0 -
1&
0%
b10 ,
b0 +
#31
b1 (
b1 -
b1 +
#32
b10 (
b10 -
b10 +
#33
b11 (
b11 -
b11 +
#34
0#
b100 (
b100 -
b100 +
#35
b101 (
b101 -
b101 +
#36
b110 (
b110 -
b110 +
#37
b111 (
b111 -
b111 +
#38
1#
b1000 (
b1000 -
b1000 +
#39
b1001 (
b1001 -
b1001 +
#40
b1010 (
b1010 -
b1010 +
#41
b1011 (
b1011 -
b1011 +
#42
0#
b1100 (
b1100 -
b1100 +
#43
b1101 (
b1101 -
b1101 +
#44
b1110 (
b1110 -
b1110 +
#45
1#
b0 (
b0 -
1%
b11 ,
b0 +
#46
b1 (
b1 -
b1 +
#47
b10 (
b10 -
b10 +
#48
b11 (
b11 -
b11 +
#49
0#
b100 (
b100 -
b100 +
#50
b101 (
b101 -
b101 +
#51
b110 (
b110 -
b110 +
#52
b111 (
b111 -
b111 +
#53
1#
b1000 (
b1000 -
b1000 +
#54
b1001 (
b1001 -
b1001 +
#55
b1010 (
b1010 -
b1010 +
#56
b1011 (
b1011 -
b1011 +
#57
0#
b1100 (
b1100 -
b1100 +
#58
b1101 (
b1101 -
b1101 +
#59
b1110 (
b1110 -
b1110 +
#60
1!
b0 (
b0 -
1'
0&
0%
b100 ,
b0 +
#61
0"
b1 (
b1 -
b1 +
#62
1"
0!
b10 (
b10 -
b10 +
#63
0"
b11 (
b11 -
b11 +
#64
1"
1!
b100 (
b100 -
b100 +
#65
0"
b101 (
b101 -
b101 +
#66
1"
0!
b110 (
b110 -
b110 +
#67
0"
b111 (
b111 -
b111 +
#68
1"
1!
b1000 (
b1000 -
b1000 +
#69
0"
b1001 (
b1001 -
b1001 +
#70
1"
0!
b1010 (
b1010 -
b1010 +
#71
0"
b1011 (
b1011 -
b1011 +
#72
1"
1!
b1100 (
b1100 -
b1100 +
#73
0"
b1101 (
b1101 -
b1101 +
#74
1"
0!
b1110 (
b1110 -
b1110 +
#75
1!
b0 (
b0 -
1%
b101 ,
b0 +
#76
b1 (
b1 -
b1 +
#77
b10 (
b10 -
b10 +
#78
b11 (
b11 -
b11 +
#79
b100 (
b100 -
b100 +
#80
b101 (
b101 -
b101 +
#81
b110 (
b110 -
b110 +
#82
b111 (
b111 -
b111 +
#83
b1000 (
b1000 -
b1000 +
#84
b1001 (
b1001 -
b1001 +
#85
b1010 (
b1010 -
b1010 +
#86
b1011 (
b1011 -
b1011 +
#87
b1100 (
b1100 -
b1100 +
#88
b1101 (
b1101 -
b1101 +
#89
b1110 (
b1110 -
b1110 +
#90
b0 (
b0 -
1&
0%
b110 ,
b0 +
#91
b1 (
b1 -
b1 +
#92
b10 (
b10 -
b10 +
#93
b11 (
b11 -
b11 +
#94
b100 (
b100 -
b100 +
#95
b101 (
b101 -
b101 +
#96
b110 (
b110 -
b110 +
#97
b111 (
b111 -
b111 +
#98
b1000 (
b1000 -
b1000 +
#99
b1001 (
b1001 -
b1001 +
#100
b1010 (
b1010 -
b1010 +
#101
b1011 (
b1011 -
b1011 +
#102
b1100 (
b1100 -
b1100 +
#103
b1101 (
b1101 -
b1101 +
#104
b1110 (
b1110 -
b1110 +
#105
b0 (
b0 -
1%
b111 ,
b0 +
#106
b1 (
b1 -
b1 +
#107
b10 (
b10 -
b10 +
#108
b11 (
b11 -
b11 +
#109
b100 (
b100 -
b100 +
#110
b101 (
b101 -
b101 +
#111
b110 (
b110 -
b110 +
#112
b111 (
b111 -
b111 +
#113
b1000 (
b1000 -
b1000 +
#114
b1001 (
b1001 -
b1001 +
#115
b1010 (
b1010 -
b1010 +
#116
b1011 (
b1011 -
b1011 +
#117
b1100 (
b1100 -
b1100 +
#118
b1101 (
b1101 -
b1101 +
#119
b1110 (
b1110 -
b1110 +
#120
1!
b0 (
b0 -
1*
0'
0&
0%
b1000 ,
b0 +
#121
0"
b1 (
b1 -
b1 +
#122
1"
0!
b10 (
b10 -
b10 +
#123
0"
b11 (
b11 -
b11 +
#124
1"
1!
b100 (
b100 -
b100 +
#125
0"
b101 (
b101 -
b101 +
#126
1"
0!
b110 (
b110 -
b110 +
#127
0"
b111 (
b111 -
b111 +
#128
1"
1!
b1000 (
b1000 -
b1000 +
#129
0"
b1001 (
b1001 -
b1001 +
#130
1"
0!
b1010 (
b1010 -
b1010 +
#131
0"
b1011 (
b1011 -
b1011 +
#132
1"
1!
b1100 (
b1100 -
b1100 +
#133
0"
b1101 (
b1101 -
b1101 +
#134
1"
0!
b1110 (
b1110 -
b1110 +
#135
1!
b0 (
b0 -
1%
b1001 ,
b0 +
#136
b1 (
b1 -
b1 +
#137
b10 (
b10 -
b10 +
#138
b11 (
b11 -
b11 +
#139
b100 (
b100 -
b100 +
#140
b101 (
b101 -
b101 +
#141
b110 (
b110 -
b110 +
#142
b111 (
b111 -
b111 +
#143
b1000 (
b1000 -
b1000 +
#144
b1001 (
b1001 -
b1001 +
#145
b1010 (
b1010 -
b1010 +
#146
b1011 (
b1011 -
b1011 +
#147
b1100 (
b1100 -
b1100 +
#148
b1101 (
b1101 -
b1101 +
#149
b1110 (
b1110 -
b1110 +
#150
b0 (
b0 -
1&
0%
b1010 ,
b0 +
#151
b1 (
b1 -
b1 +
#152
b10 (
b10 -
b10 +
#153
b11 (
b11 -
b11 +
#154
b100 (
b100 -
b100 +
#155
b101 (
b101 -
b101 +
#156
b110 (
b110 -
b110 +
#157
b111 (
b111 -
b111 +
#158
b1000 (
b1000 -
b1000 +
#159
b1001 (
b1001 -
b1001 +
#160
b1010 (
b1010 -
b1010 +
#161
b1011 (
b1011 -
b1011 +
#162
b1100 (
b1100 -
b1100 +
#163
b1101 (
b1101 -
b1101 +
#164
b1110 (
b1110 -
b1110 +
#165
b0 (
b0 -
1%
b1011 ,
b0 +
#166
b1 (
b1 -
b1 +
#167
b10 (
b10 -
b10 +
#168
b11 (
b11 -
b11 +
#169
b100 (
b100 -
b100 +
#170
b101 (
b101 -
b101 +
#171
b110 (
b110 -
b110 +
#172
b111 (
b111 -
b111 +
#173
b1000 (
b1000 -
b1000 +
#174
b1001 (
b1001 -
b1001 +
#175
b1010 (
b1010 -
b1010 +
#176
b1011 (
b1011 -
b1011 +
#177
b1100 (
b1100 -
b1100 +
#178
b1101 (
b1101 -
b1101 +
#179
b1110 (
b1110 -
b1110 +
#180
1!
b0 (
b0 -
1'
0&
0%
b1100 ,
b0 +
#181
0"
b1 (
b1 -
b1 +
#182
1"
0!
b10 (
b10 -
b10 +
#183
0"
b11 (
b11 -
b11 +
#184
1"
1!
b100 (
b100 -
b100 +
#185
0"
b101 (
b101 -
b101 +
#186
1"
0!
b110 (
b110 -
b110 +
#187
0"
b111 (
b111 -
b111 +
#188
1"
1!
b1000 (
b1000 -
b1000 +
#189
0"
b1001 (
b1001 -
b1001 +
#190
1"
0!
b1010 (
b1010 -
b1010 +
#191
0"
b1011 (
b1011 -
b1011 +
#192
1"
1!
b1100 (
b1100 -
b1100 +
#193
0"
b1101 (
b1101 -
b1101 +
#194
1"
0!
b1110 (
b1110 -
b1110 +
#195
1!
b0 (
b0 -
1%
b1101 ,
b0 +
#196
b1 (
b1 -
b1 +
#197
b10 (
b10 -
b10 +
#198
b11 (
b11 -
b11 +
#199
b100 (
b100 -
b100 +
#200
b101 (
b101 -
b101 +
#201
b110 (
b110 -
b110 +
#202
b111 (
b111 -
b111 +
#203
b1000 (
b1000 -
b1000 +
#204
b1001 (
b1001 -
b1001 +
#205
b1010 (
b1010 -
b1010 +
#206
b1011 (
b1011 -
b1011 +
#207
b1100 (
b1100 -
b1100 +
#208
b1101 (
b1101 -
b1101 +
#209
b1110 (
b1110 -
b1110 +
#210
b0 (
b0 -
1&
0%
b1110 ,
b0 +
#211
b1 (
b1 -
b1 +
#212
b10 (
b10 -
b10 +
#213
b11 (
b11 -
b11 +
#214
b100 (
b100 -
b100 +
#215
b101 (
b101 -
b101 +
#216
b110 (
b110 -
b110 +
#217
b111 (
b111 -
b111 +
#218
b1000 (
b1000 -
b1000 +
#219
b1001 (
b1001 -
b1001 +
#220
b1010 (
b1010 -
b1010 +
#221
b1011 (
b1011 -
b1011 +
#222
b1100 (
b1100 -
b1100 +
#223
b1101 (
b1101 -
b1101 +
#224
b1110 (
b1110 -
b1110 +
#225
b0 (
b0 -
1%
b1111 ,
b0 +
#226
b1 (
b1 -
b1 +
#227
b10 (
b10 -
b10 +
#228
b11 (
b11 -
b11 +
#229
b100 (
b100 -
b100 +
#230
b101 (
b101 -
b101 +
#231
b110 (
b110 -
b110 +
#232
b111 (
b111 -
b111 +
#233
b1000 (
b1000 -
b1000 +
#234
b1001 (
b1001 -
b1001 +
#235
b1010 (
b1010 -
b1010 +
#236
b1011 (
b1011 -
b1011 +
#237
b1100 (
b1100 -
b1100 +
#238
b1101 (
b1101 -
b1101 +
#239
b1110 (
b1110 -
b1110 +
#240
1#
0$
1!
b0 (
b0 -
1)
0*
0'
0&
0%
b10000 ,
b0 +
#241
0"
b1 (
b1 -
b1 +
#242
1"
0!
b10 (
b10 -
b10 +
#243
0"
b11 (
b11 -
b11 +
#244
0#
1"
1!
b100 (
b100 -
b100 +
#245
0"
b101 (
b101 -
b101 +
#246
1"
0!
b110 (
b110 -
b110 +
#247
0"
b111 (
b111 -
b111 +
#248
1#
1"
1!
b1000 (
b1000 -
b1000 +
#249
0"
b1001 (
b1001 -
b1001 +
#250
1"
0!
b1010 (
b1010 -
b1010 +
#251
0"
b1011 (
b1011 -
b1011 +
#252
0#
1"
1!
b1100 (
b1100 -
b1100 +
#253
0"
b1101 (
b1101 -
b1101 +
#254
1"
0!
b1110 (
b1110 -
b1110 +
#255
1#
1!
b0 (
b0 -
1%
b10001 ,
b0 +
#256
b1 (
b1 -
b1 +
#257
b10 (
b10 -
b10 +
#258
b11 (
b11 -
b11 +
#259
0#
b100 (
b100 -
b100 +
#260
b101 (
b101 -
b101 +
#261
b110 (
b110 -
b110 +
#262
b111 (
b111 -
b111 +
#263
1#
b1000 (
b1000 -
b1000 +
#264
b1001 (
b1001 -
b1001 +
#265
b1010 (
b1010 -
b1010 +
#266
b1011 (
b1011 -
b1011 +
#267
0#
b1100 (
b1100 -
b1100 +
#268
b1101 (
b1101 -
b1101 +
#269
b1110 (
b1110 -
b1110 +
#270
1#
b0 (
b0 -
1&
0%
b10010 ,
b0 +
#271
b1 (
b1 -
b1 +
#272
b10 (
b10 -
b10 +
#273
b11 (
b11 -
b11 +
#274
0#
b100 (
b100 -
b100 +
#275
b101 (
b101 -
b101 +
#276
b110 (
b110 -
b110 +
#277
b111 (
b111 -
b111 +
#278
1#
b1000 (
b1000 -
b1000 +
#279
b1001 (
b1001 -
b1001 +
#280
b1010 (
b1010 -
b1010 +
#281
b1011 (
b1011 -
b1011 +
#282
0#
b1100 (
b1100 -
b1100 +
#283
b1101 (
b1101 -
b1101 +
#284
b1110 (
b1110 -
b1110 +
#285
1#
b0 (
b0 -
1%
b10011 ,
b0 +
#286
b1 (
b1 -
b1 +
#287
b10 (
b10 -
b10 +
#288
b11 (
b11 -
b11 +
#289
0#
b100 (
b100 -
b100 +
#290
b101 (
b101 -
b101 +
#291
b110 (
b110 -
b110 +
#292
b111 (
b111 -
b111 +
#293
1#
b1000 (
b1000 -
b1000 +
#294
b1001 (
b1001 -
b1001 +
#295
b1010 (
b1010 -
b1010 +
#296
b1011 (
b1011 -
b1011 +
#297
0#
b1100 (
b1100 -
b1100 +
#298
b1101 (
b1101 -
b1101 +
#299
b1110 (
b1110 -
b1110 +
#300
1!
b0 (
b0 -
1'
0&
0%
b10100 ,
b0 +
#301
0"
b1 (
b1 -
b1 +
#302
1"
0!
b10 (
b10 -
b10 +
#303
0"
b11 (
b11 -
b11 +
#304
1"
1!
b100 (
b100 -
b100 +
#305
0"
b101 (
b101 -
b101 +
#306
1"
0!
b110 (
b110 -
b110 +
#307
0"
b111 (
b111 -
b111 +
#308
1"
1!
b1000 (
b1000 -
b1000 +
#309
0"
b1001 (
b1001 -
b1001 +
#310
1"
0!
b1010 (
b1010 -
b1010 +
#311
0"
b1011 (
b1011 -
b1011 +
#312
1"
1!
b1100 (
b1100 -
b1100 +
#313
0"
b1101 (
b1101 -
b1101 +
#314
1"
0!
b1110 (
b1110 -
b1110 +
#315
1!
b0 (
b0 -
1%
b10101 ,
b0 +
#316
b1 (
b1 -
b1 +
#317
b10 (
b10 -
b10 +
#318
b11 (
b11 -
b11 +
#319
b100 (
b100 -
b100 +
#320
b101 (
b101 -
b101 +
#321
b110 (
b110 -
b110 +
#322
b111 (
b111 -
b111 +
#323
b1000 (
b1000 -
b1000 +
#324
b1001 (
b1001 -
b1001 +
#325
b1010 (
b1010 -
b1010 +
#326
b1011 (
b1011 -
b1011 +
#327
b1100 (
b1100 -
b1100 +
#328
b1101 (
b1101 -
b1101 +
#329
b1110 (
b1110 -
b1110 +
#330
b0 (
b0 -
1&
0%
b10110 ,
b0 +
#331
b1 (
b1 -
b1 +
#332
b10 (
b10 -
b10 +
#333
b11 (
b11 -
b11 +
#334
b100 (
b100 -
b100 +
#335
b101 (
b101 -
b101 +
#336
b110 (
b110 -
b110 +
#337
b111 (
b111 -
b111 +
#338
b1000 (
b1000 -
b1000 +
#339
b1001 (
b1001 -
b1001 +
#340
b1010 (
b1010 -
b1010 +
#341
b1011 (
b1011 -
b1011 +
#342
b1100 (
b1100 -
b1100 +
#343
b1101 (
b1101 -
b1101 +
#344
b1110 (
b1110 -
b1110 +
#345
b0 (
b0 -
1%
b10111 ,
b0 +
#346
b1 (
b1 -
b1 +
#347
b10 (
b10 -
b10 +
#348
b11 (
b11 -
b11 +
#349
b100 (
b100 -
b100 +
#350
b101 (
b101 -
b101 +
#351
b110 (
b110 -
b110 +
#352
b111 (
b111 -
b111 +
#353
b1000 (
b1000 -
b1000 +
#354
b1001 (
b1001 -
b1001 +
#355
b1010 (
b1010 -
b1010 +
#356
b1011 (
b1011 -
b1011 +
#357
b1100 (
b1100 -
b1100 +
#358
b1101 (
b1101 -
b1101 +
#359
b1110 (
b1110 -
b1110 +
#360
1!
b0 (
b0 -
1*
0'
0&
0%
b11000 ,
b0 +
#361
0"
b1 (
b1 -
b1 +
#362
1"
0!
b10 (
b10 -
b10 +
#363
0"
b11 (
b11 -
b11 +
#364
1"
1!
b100 (
b100 -
b100 +
#365
0"
b101 (
b101 -
b101 +
#366
1"
0!
b110 (
b110 -
b110 +
#367
0"
b111 (
b111 -
b111 +
#368
1"
1!
b1000 (
b1000 -
b1000 +
#369
0"
b1001 (
b1001 -
b1001 +
#370
1"
0!
b1010 (
b1010 -
b1010 +
#371
0"
b1011 (
b1011 -
b1011 +
#372
1"
1!
b1100 (
b1100 -
b1100 +
#373
0"
b1101 (
b1101 -
b1101 +
#374
1"
0!
b1110 (
b1110 -
b1110 +
#375
1!
b0 (
b0 -
1%
b11001 ,
b0 +
#376
b1 (
b1 -
b1 +
#377
b10 (
b10 -
b10 +
#378
b11 (
b11 -
b11 +
#379
b100 (
b100 -
b100 +
#380
b101 (
b101 -
b101 +
#381
b110 (
b110 -
b110 +
#382
b111 (
b111 -
b111 +
#383
b1000 (
b1000 -
b1000 +
#384
b1001 (
b1001 -
b1001 +
#385
b1010 (
b1010 -
b1010 +
#386
b1011 (
b1011 -
b1011 +
#387
b1100 (
b1100 -
b1100 +
#388
b1101 (
b1101 -
b1101 +
#389
b1110 (
b1110 -
b1110 +
#390
b0 (
b0 -
1&
0%
b11010 ,
b0 +
#391
b1 (
b1 -
b1 +
#392
b10 (
b10 -
b10 +
#393
b11 (
b11 -
b11 +
#394
b100 (
b100 -
b100 +
#395
b101 (
b101 -
b101 +
#396
b110 (
b110 -
b110 +
#397
b111 (
b111 -
b111 +
#398
b1000 (
b1000 -
b1000 +
#399
b1001 (
b1001 -
b1001 +
#400
b1010 (
b1010 -
b1010 +
#401
b1011 (
b1011 -
b1011 +
#402
b1100 (
b1100 -
b1100 +
#403
b1101 (
b1101 -
b1101 +
#404
b1110 (
b1110 -
b1110 +
#405
b0 (
b0 -
1%
b11011 ,
b0 +
#406
b1 (
b1 -
b1 +
#407
b10 (
b10 -
b10 +
#408
b11 (
b11 -
b11 +
#409
b100 (
b100 -
b100 +
#410
b101 (
b101 -
b101 +
#411
b110 (
b110 -
b110 +
#412
b111 (
b111 -
b111 +
#413
b1000 (
b1000 -
b1000 +
#414
b1001 (
b1001 -
b1001 +
#415
b1010 (
b1010 -
b1010 +
#416
b1011 (
b1011 -
b1011 +
#417
b1100 (
b1100 -
b1100 +
#418
b1101 (
b1101 -
b1101 +
#419
b1110 (
b1110 -
b1110 +
#420
1!
b0 (
b0 -
1'
0&
0%
b11100 ,
b0 +
#421
0"
b1 (
b1 -
b1 +
#422
1"
0!
b10 (
b10 -
b10 +
#423
0"
b11 (
b11 -
b11 +
#424
1"
1!
b100 (
b100 -
b100 +
#425
0"
b101 (
b101 -
b101 +
#426
1"
0!
b110 (
b110 -
b110 +
#427
0"
b111 (
b111 -
b111 +
#428
1"
1!
b1000 (
b1000 -
b1000 +
#429
0"
b1001 (
b1001 -
b1001 +
#430
1"
0!
b1010 (
b1010 -
b1010 +
#431
0"
b1011 (
b1011 -
b1011 +
#432
1"
1!
b1100 (
b1100 -
b1100 +
#433
0"
b1101 (
b1101 -
b1101 +
#434
1"
0!
b1110 (
b1110 -
b1110 +
#435
1!
b0 (
b0 -
1%
b11101 ,
b0 +
#436
b1 (
b1 -
b1 +
#437
b10 (
b10 -
b10 +
#438
b11 (
b11 -
b11 +
#439
b100 (
b100 -
b100 +
#440
b101 (
b101 -
b101 +
#441
b110 (
b110 -
b110 +
#442
b111 (
b111 -
b111 +
#443
b1000 (
b1000 -
b1000 +
#444
b1001 (
b1001 -
b1001 +
#445
b1010 (
b1010 -
b1010 +
#446
b1011 (
b1011 -
b1011 +
#447
b1100 (
b1100 -
b1100 +
#448
b1101 (
b1101 -
b1101 +
#449
b1110 (
b1110 -
b1110 +
#450
b0 (
b0 -
1&
0%
b11110 ,
b0 +
#451
b1 (
b1 -
b1 +
#452
b10 (
b10 -
b10 +
#453
b11 (
b11 -
b11 +
#454
b100 (
b100 -
b100 +
#455
b101 (
b101 -
b101 +
#456
b110 (
b110 -
b110 +
#457
b111 (
b111 -
b111 +
#458
b1000 (
b1000 -
b1000 +
#459
b1001 (
b1001 -
b1001 +
#460
b1010 (
b1010 -
b1010 +
#461
b1011 (
b1011 -
b1011 +
#462
b1100 (
b1100 -
b1100 +
#463
b1101 (
b1101 -
b1101 +
#464
b1110 (
b1110 -
b1110 +
#465
b11111 ,
b1111 +
